kuflow_temporal_worker/__init__.py
kuflow_temporal_worker/_authentication.py
kuflow_temporal_worker/_connection.py
kuflow_temporal_worker/_connection_config.py
kuflow_temporal_worker/_encryption/__init__.py
kuflow_temporal_worker/_encryption/_kuflow_cache.py
kuflow_temporal_worker/_encryption/_kuflow_crypto.py
kuflow_temporal_worker/_encryption/_kuflow_encryption_instrumentation.py
kuflow_temporal_worker/_encryption/_kuflow_encryption_interceptor.py
kuflow_temporal_worker/_encryption/_kuflow_encryption_payload_codec.py
kuflow_temporal_worker/_encryption/_kuflow_encryption_payload_converter.py
kuflow_temporal_worker/_worker_information_notifier.py
kuflow_temporal_worker-3.2.1.dist-info/METADATA
kuflow_temporal_worker-3.2.1.dist-info/WHEEL
kuflow_temporal_worker-3.2.1.dist-info/RECORD
