Metadata-Version: 2.3
Name: kuflow-temporal-worker
Version: 3.2.1
Summary: KuFlow utilities to use Temporal.io
License: MIT
Author: KuFlow S.L.
Author-email: kuflow@kuflow.com
Requires-Python: >=3.9,<4.0
Classifier: License :: OSI Approved :: MIT License
Classifier: Programming Language :: Python :: 3
Classifier: Programming Language :: Python :: 3.9
Classifier: Programming Language :: Python :: 3.10
Classifier: Programming Language :: Python :: 3.11
Classifier: Programming Language :: Python :: 3.12
Classifier: Programming Language :: Python :: 3.13
Requires-Dist: cryptography (>=38.0.1)
Requires-Dist: kuflow-temporal-common (>=3.2.1,<4.0.0)
Requires-Dist: temporalio (>=1.10.0,<1.11.0)
Project-URL: Documentation, https://docs.kuflow.com/
Project-URL: Homepage, https://kuflow.com/
Project-URL: Repository, https://github.com/kuflow/kuflow-sdk-python
